pse_core/__init__.py
pse_core/engine.py
pse_core/pse_core.cp311-win_amd64.pyd
pse_core/pse_core.pyi
pse_core/py.typed
pse_core/state_machine.py
pse_core/stepper.py
pse_core/stepper_delta.py
pse_core/trie.py
include/eigen3/signature_of_eigen3_matrix_library
include/eigen3/Eigen/AccelerateSupport
include/eigen3/Eigen/Cholesky
include/eigen3/Eigen/CholmodSupport
include/eigen3/Eigen/Core
include/eigen3/Eigen/Dense
include/eigen3/Eigen/Eigen
include/eigen3/Eigen/Eigenvalues
include/eigen3/Eigen/Geometry
include/eigen3/Eigen/Householder
include/eigen3/Eigen/IterativeLinearSolvers
include/eigen3/Eigen/Jacobi
include/eigen3/Eigen/KLUSupport
include/eigen3/Eigen/LU
include/eigen3/Eigen/MetisSupport
include/eigen3/Eigen/OrderingMethods
include/eigen3/Eigen/PaStiXSupport
include/eigen3/Eigen/PardisoSupport
include/eigen3/Eigen/QR
include/eigen3/Eigen/QtAlignedMalloc
include/eigen3/Eigen/SPQRSupport
include/eigen3/Eigen/SVD
include/eigen3/Eigen/Sparse
include/eigen3/Eigen/SparseCholesky
include/eigen3/Eigen/SparseCore
include/eigen3/Eigen/SparseLU
include/eigen3/Eigen/SparseQR
include/eigen3/Eigen/StdDeque
include/eigen3/Eigen/StdList
include/eigen3/Eigen/StdVector
include/eigen3/Eigen/SuperLUSupport
include/eigen3/Eigen/ThreadPool
include/eigen3/Eigen/UmfPackSupport
pse_core/sdk/cmake/pse_coreConfig.cmake
pse_core/sdk/cmake/pse_coreConfigVersion.cmake
pse_core/sdk/cmake/pse_coreTargets-release.cmake
pse_core/sdk/cmake/pse_coreTargets.cmake
pse_core/sdk/include/dtypes.h
pse_core/sdk/include/engine.h
pse_core/sdk/include/state_machine.h
pse_core/sdk/include/state_machine_trampoline.h
pse_core/sdk/include/stepper.h
pse_core/sdk/include/stepper_delta.h
pse_core/sdk/include/stepper_trampoline.h
pse_core/sdk/lib/pse_sdk.lib
include/eigen3/unsupported/Eigen/AdolcForward
include/eigen3/unsupported/Eigen/AlignedVector3
include/eigen3/unsupported/Eigen/ArpackSupport
include/eigen3/unsupported/Eigen/AutoDiff
include/eigen3/unsupported/Eigen/BVH
pse_core-2025.6.1.dist-info/LICENSE
pse_core-2025.6.1.dist-info/METADATA
pse_core-2025.6.1.dist-info/WHEEL
pse_core-2025.6.1.dist-info/entry_points.txt
pse_core-2025.6.1.dist-info/RECORD
