Metadata-Version: 2.1
Name: pse-core
Version: 2025.6.1
Summary: Proxy Structuring Engine: Core library
Author-Email: Jack Wind <jckwind11@gmail.com>, The Proxy Company <contact@theproxy.company>
License: (c) 2024 the proxy company. all rights reserved.
Requires-Python: >=3.11
